aiedatools/__init__.py
aiedatools/bigquery_data_prepare.py
aiedatools/single_variable_analysis.py
aiedatools/table_schema_search.py
aiedatools/trend_analysis.py
aiedatools/two_variables_analysis.py
aiedatools-0.1.1.dist-info/licenses/LICENSE
aiedatools-0.1.1.dist-info/METADATA
aiedatools-0.1.1.dist-info/WHEEL
aiedatools-0.1.1.dist-info/top_level.txt
aiedatools-0.1.1.dist-info/RECORD
