Metadata-Version: 2.4
Name: aiedatools
Version: 0.1.1
Summary: A modern, open-source Python library built for efficient, scalable data profiling and visualization
Author-email: "Dr. Mathesis" <dr.mathesis@outlook.com>
License: LICENSE
Project-URL: Homepage, https://github.com/mathesis-universe/aiedatools
Requires-Python: >=3.10
License-File: LICENSE
Requires-Dist: numpy>=2.0.0
Requires-Dist: pandas>=2.2.2
Requires-Dist: polars
Requires-Dist: duckdb
Requires-Dist: plotly
Requires-Dist: scipy
Requires-Dist: pyarrow
Requires-Dist: google-cloud-bigquery
Requires-Dist: sentence-transformers
Dynamic: license-file
